cr_analysis/VERSION
cr_analysis/__init__.py
cr_analysis/config.yml
cr_analysis/evaluate.py
cr_analysis/pipeline.py
cr_analysis/predict.py
cr_analysis/train.py
cr_analysis/config/__init__.py
cr_analysis/config/core.py
cr_analysis/datasets/__init__.py
cr_analysis/datasets/raw/test.csv
cr_analysis/datasets/raw/train.csv
cr_analysis/processing/__init__.py
cr_analysis/processing/data_manager.py
cr_analysis/processing/features.py
cr_analysis/processing/preprocessing.py
cr_analysis/trained_models/cr_pipeline_v0.0.3.pkl
tid_costa_rica_poverty_prediction-0.0.3.dist-info/LICENSE
tid_costa_rica_poverty_prediction-0.0.3.dist-info/METADATA
tid_costa_rica_poverty_prediction-0.0.3.dist-info/WHEEL
tid_costa_rica_poverty_prediction-0.0.3.dist-info/top_level.txt
tid_costa_rica_poverty_prediction-0.0.3.dist-info/RECORD
