Metadata-Version: 2.1
Name: tid-costa-rica-poverty-prediction
Version: 0.0.3
Summary: Train a Random Forest model to predict poverty level of costa rican household based on their demographic characteristics
Home-page: https://github.com/hfung4/Data-Projects/tree/master/costa_rican_poverty_classifier/prod_proj_final
Author: HenryF
Author-email: henryhfung21@gmail.com
License: BSD-3
Classifier: License :: OSI Approved :: MIT License
Classifier: Programming Language :: Python
Classifier: Programming Language :: Python :: 3
Classifier: Programming Language :: Python :: 3.6
Classifier: Programming Language :: Python :: 3.7
Classifier: Programming Language :: Python :: 3.8
Classifier: Programming Language :: Python :: 3.9
Classifier: Programming Language :: Python :: 3.10
Classifier: Programming Language :: Python :: Implementation :: CPython
Classifier: Programming Language :: Python :: Implementation :: PyPy
Requires-Python: >=3.10.5
License-File: LICENSE
Requires-Dist: altair (==4.2.0)
Requires-Dist: appnope (==0.1.3)
Requires-Dist: argon2-cffi (==21.3.0)
Requires-Dist: argon2-cffi-bindings (==21.2.0)
Requires-Dist: asttokens (==2.0.5)
Requires-Dist: attrs (==21.4.0)
Requires-Dist: backcall (==0.2.0)
Requires-Dist: beautifulsoup4 (==4.11.1)
Requires-Dist: bleach (==5.0.0)
Requires-Dist: blinker (==1.5)
Requires-Dist: cachetools (==5.2.0)
Requires-Dist: certifi (==2022.6.15)
Requires-Dist: cffi (==1.15.0)
Requires-Dist: chardet (==5.1.0)
Requires-Dist: charset-normalizer (==2.1.0)
Requires-Dist: click (==8.1.3)
Requires-Dist: colorama (==0.4.6)
Requires-Dist: commonmark (==0.9.1)
Requires-Dist: cycler (==0.11.0)
Requires-Dist: debugpy (==1.6.0)
Requires-Dist: decorator (==5.1.1)
Requires-Dist: defusedxml (==0.7.1)
Requires-Dist: distlib (==0.3.6)
Requires-Dist: entrypoints (==0.4)
Requires-Dist: execnet (==1.9.0)
Requires-Dist: executing (==0.8.3)
Requires-Dist: fastjsonschema (==2.15.3)
Requires-Dist: feature-engine (==1.4.1)
Requires-Dist: filelock (==3.9.0)
Requires-Dist: fonttools (==4.33.3)
Requires-Dist: gitdb (==4.0.9)
Requires-Dist: GitPython (==3.1.27)
Requires-Dist: idna (==3.3)
Requires-Dist: imbalanced-learn (==0.9.1)
Requires-Dist: imblearn (==0.0)
Requires-Dist: importlib-metadata (==4.12.0)
Requires-Dist: iniconfig (==1.1.1)
Requires-Dist: ipykernel (==6.13.0)
Requires-Dist: ipython (==8.3.0)
Requires-Dist: ipython-genutils (==0.2.0)
Requires-Dist: ipywidgets (==7.7.0)
Requires-Dist: jedi (==0.18.1)
Requires-Dist: Jinja2 (==3.1.2)
Requires-Dist: joblib (==1.1.0)
Requires-Dist: jsonschema (==4.5.1)
Requires-Dist: jupyter (==1.0.0)
Requires-Dist: jupyter-client (==7.3.1)
Requires-Dist: jupyter-console (==6.4.3)
Requires-Dist: jupyter-contrib-core (==0.3.3)
Requires-Dist: jupyter-contrib-nbextensions (==0.5.1)
Requires-Dist: jupyter-core (==4.10.0)
Requires-Dist: jupyter-highlight-selected-word (==0.2.0)
Requires-Dist: jupyter-latex-envs (==1.4.6)
Requires-Dist: jupyter-nbextensions-configurator (==0.4.1)
Requires-Dist: jupyterlab-pygments (==0.2.2)
Requires-Dist: jupyterlab-widgets (==1.1.0)
Requires-Dist: kiwisolver (==1.4.2)
Requires-Dist: lightgbm (==3.3.2)
Requires-Dist: lxml (==4.9.0)
Requires-Dist: MarkupSafe (==2.1.1)
Requires-Dist: matplotlib (==3.5.2)
Requires-Dist: matplotlib-inline (==0.1.3)
Requires-Dist: mistune (==0.8.4)
Requires-Dist: mypy-extensions (==0.4.3)
Requires-Dist: nbclient (==0.6.3)
Requires-Dist: nbconvert (==6.5.0)
Requires-Dist: nbformat (==5.4.0)
Requires-Dist: nest-asyncio (==1.5.5)
Requires-Dist: nltk (==3.7)
Requires-Dist: notebook (==6.4.11)
Requires-Dist: numpy (==1.22.3)
Requires-Dist: packaging (==22.0)
Requires-Dist: pandas (==1.4.2)
Requires-Dist: pandocfilters (==1.5.0)
Requires-Dist: parso (==0.8.3)
Requires-Dist: pathspec (==0.10.2)
Requires-Dist: patsy (==0.5.2)
Requires-Dist: pexpect (==4.8.0)
Requires-Dist: pickleshare (==0.7.5)
Requires-Dist: Pillow (==9.1.0)
Requires-Dist: platformdirs (==2.6.2)
Requires-Dist: plotly (==5.10.0)
Requires-Dist: pluggy (==1.0.0)
Requires-Dist: prometheus-client (==0.14.1)
Requires-Dist: prompt-toolkit (==3.0.29)
Requires-Dist: protobuf (==3.20.1)
Requires-Dist: psutil (==5.9.0)
Requires-Dist: ptyprocess (==0.7.0)
Requires-Dist: pure-eval (==0.2.2)
Requires-Dist: py (==1.11.0)
Requires-Dist: pyarrow (==9.0.0)
Requires-Dist: pycparser (==2.21)
Requires-Dist: pydantic (==1.10.2)
Requires-Dist: pydeck (==0.7.1)
Requires-Dist: Pygments (==2.12.0)
Requires-Dist: Pympler (==1.0.1)
Requires-Dist: pyparsing (==3.0.9)
Requires-Dist: pyproject-api (==1.4.0)
Requires-Dist: pyrsistent (==0.18.1)
Requires-Dist: pytest (==7.1.2)
Requires-Dist: pytest-forked (==1.4.0)
Requires-Dist: pytest-xdist (==2.5.0)
Requires-Dist: python-dateutil (==2.8.2)
Requires-Dist: pytz (==2022.1)
Requires-Dist: pytz-deprecation-shim (==0.1.0.post0)
Requires-Dist: PyYAML (==6.0)
Requires-Dist: pyzmq (==22.3.0)
Requires-Dist: qtconsole (==5.3.0)
Requires-Dist: QtPy (==2.1.0)
Requires-Dist: regex (==2022.8.17)
Requires-Dist: requests (==2.28.1)
Requires-Dist: rich (==12.5.1)
Requires-Dist: scikit-learn (==1.1.3)
Requires-Dist: scipy (==1.8.0)
Requires-Dist: seaborn (==0.11.2)
Requires-Dist: semver (==2.13.0)
Requires-Dist: Send2Trash (==1.8.0)
Requires-Dist: six (==1.16.0)
Requires-Dist: smmap (==5.0.0)
Requires-Dist: soupsieve (==2.3.2.post1)
Requires-Dist: stack-data (==0.2.0)
Requires-Dist: statsmodels (==0.13.2)
Requires-Dist: streamlit (==1.12.0)
Requires-Dist: strictyaml (==1.6.2)
Requires-Dist: tenacity (==8.0.1)
Requires-Dist: terminado (==0.13.3)
Requires-Dist: threadpoolctl (==3.1.0)
Requires-Dist: tinycss2 (==1.1.1)
Requires-Dist: toml (==0.10.2)
Requires-Dist: tomli (==2.0.1)
Requires-Dist: toolz (==0.12.0)
Requires-Dist: tornado (==6.1)
Requires-Dist: tox (==4.2.3)
Requires-Dist: tqdm (==4.64.0)
Requires-Dist: traitlets (==5.2.0)
Requires-Dist: typing-extensions (==4.3.0)
Requires-Dist: tzdata (==2022.2)
Requires-Dist: tzlocal (==4.2)
Requires-Dist: urllib3 (==1.26.11)
Requires-Dist: validators (==0.20.0)
Requires-Dist: virtualenv (==20.17.1)
Requires-Dist: wcwidth (==0.2.5)
Requires-Dist: webencodings (==0.5.1)
Requires-Dist: widgetsnbextension (==3.6.0)
Requires-Dist: wordcloud (==1.8.2.2)
Requires-Dist: zipp (==3.8.1)
Requires-Dist: black (==22.10.0)
